{
  "formatVersion": 1,
  "database": {
    "version": 1,
    "identityHash": "88b6e6b07aca780849d5fb5576bde7cb",
    "entities": [
      {
        "tableName": "planned",
        "createSql": "CREATE TABLE IF NOT EXISTS `${TABLE_NAME}` (`id` INTEGER PRIMARY KEY AUTOINCREMENT NOT NULL, `date` TEXT, `startTime` TEXT, `endTime` TEXT, `eventName` TEXT)",
        "fields": [
          {
            "fieldPath": "id",
            "columnName": "id",
            "affinity": "INTEGER",
            "notNull": true
          },
          {
            "fieldPath": "date",
            "columnName": "date",
            "affinity": "TEXT",
            "notNull": false
          },
          {
            "fieldPath": "startTime",
            "columnName": "startTime",
            "affinity": "TEXT",
            "notNull": false
          },
          {
            "fieldPath": "endTime",
            "columnName": "endTime",
            "affinity": "TEXT",
            "notNull": false
          },
          {
            "fieldPath": "eventName",
            "columnName": "eventName",
            "affinity": "TEXT",
            "notNull": false
          }
        ],
        "primaryKey": {
          "columnNames": [
            "id"
          ],
          "autoGenerate": true
        },
        "indices": [],
        "foreignKeys": []
      },
      {
        "tableName": "unplanned",
        "createSql": "CREATE TABLE IF NOT EXISTS `${TABLE_NAME}` (`id` INTEGER NOT NULL, `dueDate` TEXT, `dueTime` TEXT, `duration` TEXT, `taskName` TEXT)",
        "fields": [
          {
            "fieldPath": "id",
            "columnName": "id",
            "affinity": "INTEGER",
            "notNull": true
          },
          {
            "fieldPath": "dueDate",
            "columnName": "dueDate",
            "affinity": "TEXT",
            "notNull": false
          },
          {
            "fieldPath": "dueTime",
            "columnName": "dueTime",
            "affinity": "TEXT",
            "notNull": false
          },
          {
            "fieldPath": "duration",
            "columnName": "duration",
            "affinity": "TEXT",
            "notNull": false
          },
          {
            "fieldPath": "taskName",
            "columnName": "taskName",
            "affinity": "TEXT",
            "notNull": false
          }
        ],
        "primaryKey": {
          "columnNames": [],
          "autoGenerate": false
        },
        "indices": [],
        "foreignKeys": []
      }
    ],
    "views": [],
    "setupQueries": [
      "CREATE TABLE IF NOT EXISTS room_master_table (id INTEGER PRIMARY KEY,identity_hash TEXT)",
      "INSERT OR REPLACE INTO room_master_table (id,identity_hash) VALUES(42, '88b6e6b07aca780849d5fb5576bde7cb')"
    ]
  }
}